.DS_Store
fa_kit/__init__.py
fa_kit/broken_stick.py
fa_kit/extraction.py
fa_kit/factor_analysis.py
fa_kit/plotting.py
fa_kit/retention.py
fa_kit/rotation.py
fa_kit/rotation_tf.py
fa_kit-0.1.2.dist-info/DESCRIPTION.rst
fa_kit-0.1.2.dist-info/METADATA
fa_kit-0.1.2.dist-info/RECORD
fa_kit-0.1.2.dist-info/WHEEL
fa_kit-0.1.2.dist-info/metadata.json
fa_kit-0.1.2.dist-info/top_level.txt
