Metadata-Version: 2.0
Name: fa-kit
Version: 0.1.2
Summary: Factor Analysis Kit
Home-page: https://github.com/bmcmenamin/fa_kit
Author: Brenton McMenamin
Author-email: bmcmenamin+fa_kit@gmail.com
License: MIT
Keywords: factor analysis pca varimax quartimax rotation
Platform: UNKNOWN
Classifier: Development Status :: 3 - Alpha
Classifier: Intended Audience :: Science/Research
Classifier: Topic :: Scientific/Engineering :: Information Analysis
Classifier: License :: OSI Approved :: MIT License
Classifier: Programming Language :: Python :: 2
Classifier: Programming Language :: Python :: 2.7
Classifier: Programming Language :: Python :: 3
Classifier: Programming Language :: Python :: 3.3
Classifier: Programming Language :: Python :: 3.4
Classifier: Programming Language :: Python :: 3.5
Requires-Dist: numpy
Requires-Dist: scipy
Requires-Dist: pandas
Requires-Dist: matplotlib
Provides-Extra: examples
Requires-Dist: jupyter; extra == 'examples'
Provides-Extra: tf
Requires-Dist: tensorflow; extra == 'tf'
